{
  "id": "e0c852d4403f4da0b7a18efdb2382c5d",
  "title": "1一楼阅览室-自习室.png",
  "width": 10000,
  "height": 10000,
  "minZoom": 0,
  "maxZoom": 5,
  "tileSize": 512,
  "extent": [
    0.0,
    -10000.0,
    10000.0,
    0.0
  ],
  "origin": [
    0.0,
    0.0
  ],
  "resolutions": [
    32.0,
    16.0,
    8.0,
    4.0,
    2.0,
    1.0
  ],
  "center": [
    5000.0,
    -5000.0
  ],
  "initialResolution": 32.0,
  "urlTemplate": "http://0.0.0.0:8000/api/tiles/e0c852d4403f4da0b7a18efdb2382c5d/{z}/{x}/{y}.png",
  "manifestUrl": "http://0.0.0.0:8000/api/tiles/e0c852d4403f4da0b7a18efdb2382c5d/manifest",
  "tileFormat": "png",
  "scheme": "xyz",
  "projection": "pixel",
  "bounds": [
    0.0,
    0.0,
    10000.0,
    10000.0
  ],
  "generatedBy": "gdal2tiles",
  "note": null
}